pymocker/__init__.py
pymocker/builder/__init__.py
pymocker/builder/coercers.py
pymocker/builder/extensible.py
pymocker/builder/mixins.py
pymocker/builder/rank.py
pymocker/builder/utils.py
pymocker/builder/validators.py
pymocker/mocker.py
pymocker/mocker.pyi
pymocker-0.1.7.dist-info/METADATA
pymocker-0.1.7.dist-info/WHEEL
pymocker-0.1.7.dist-info/licenses/LICENSE
pymocker-0.1.7.dist-info/RECORD
