Metadata-Version: 2.4
Name: pymocker
Version: 0.1.7
Summary: Generate realistic, context-aware mock data automatically.
License: Apache 2.0
License-File: LICENSE
Author: eschallack
Author-email: evan.schallack@gmail.com
Requires-Python: >=3.13
Classifier: License :: Other/Proprietary License
Classifier: Programming Language :: Python :: 3
Classifier: Programming Language :: Python :: 3.13
Classifier: Programming Language :: Python :: 3.14
Requires-Dist: Faker (>=25.6.0,<26.0.0)
Requires-Dist: SQLAlchemy (>=2.0.29,<3.0.0)
Requires-Dist: polyfactory (>=2.15.2,<3.0.0)
Requires-Dist: pydantic (>=2.7.1,<3.0.0)
Requires-Dist: sentence-transformers (>=2.7.0,<3.0.0)
Requires-Dist: wordsegment (>=1.3.1,<2.0.0)
